plone.scale-4.2.1-py3.13-nspkg.pth
plone/scale/__init__.py
plone/scale/interfaces.py
plone/scale/scale.py
plone/scale/storage.py
plone/scale/tests/__init__.py
plone/scale/tests/test_scale.py
plone/scale/tests/test_storage.py
plone/scale/tests/data/animated.gif
plone/scale/tests/data/animated2.gif
plone/scale/tests/data/cmyk.jpg
plone/scale/tests/data/greyscale_image.png
plone/scale/tests/data/logo.gif
plone/scale/tests/data/logo.png
plone/scale/tests/data/logo.tiff
plone/scale/tests/data/profile.jpg
plone/scale/tests/data/profile.webp
plone_scale-4.2.1.dist-info/METADATA
plone_scale-4.2.1.dist-info/WHEEL
plone_scale-4.2.1.dist-info/namespace_packages.txt
plone_scale-4.2.1.dist-info/top_level.txt
plone_scale-4.2.1.dist-info/RECORD
