Metadata-Version: 2.4
Name: plone.scale
Version: 4.2.1
Summary: Image scaling
Home-page: https://pypi.org/project/plone.scale
Author: Plone Foundation
Author-email: plone-developers@lists.sourceforge.net
License: BSD
Keywords: image scaling
Classifier: Development Status :: 5 - Production/Stable
Classifier: Environment :: Web Environment
Classifier: Framework :: Plone
Classifier: Framework :: Plone :: 6.0
Classifier: Framework :: Plone :: Core
Classifier: Framework :: Zope :: 5
Classifier: License :: OSI Approved :: BSD License
Classifier: Operating System :: OS Independent
Classifier: Programming Language :: Python
Classifier: Programming Language :: Python :: 3.8
Classifier: Programming Language :: Python :: 3.9
Classifier: Programming Language :: Python :: 3.10
Classifier: Programming Language :: Python :: 3.11
Requires-Python: >=3.8
Requires-Dist: Pillow
Requires-Dist: lxml
Requires-Dist: setuptools
Requires-Dist: zope.annotation
Requires-Dist: zope.interface
Provides-Extra: storage
Requires-Dist: ZODB; extra == "storage"
Requires-Dist: persistent; extra == "storage"
Provides-Extra: test
Requires-Dist: ZODB; extra == "test"
Requires-Dist: persistent; extra == "test"
Requires-Dist: zope.component; extra == "test"
Requires-Dist: plone.testing[test]; extra == "test"
Dynamic: author
Dynamic: author-email
Dynamic: classifier
Dynamic: description
Dynamic: description-content-type
Dynamic: home-page
Dynamic: keywords
Dynamic: license
Dynamic: provides-extra
Dynamic: requires-dist
Dynamic: requires-python
Dynamic: summary
